EO_Floods/__init__.py
EO_Floods/auth.py
EO_Floods/dataset.py
EO_Floods/floodmap.py
EO_Floods/provider.py
EO_Floods/utils.py
eo_floods-2023.12.dist-info/LICENSE
eo_floods-2023.12.dist-info/WHEEL
eo_floods-2023.12.dist-info/METADATA
eo_floods-2023.12.dist-info/RECORD
