Metadata-Version: 2.1
Name: EO_Floods
Version: 2023.12
Summary: An easy to use interface for deriving flood maps from earth observation data
Author-email: Tjalling de jong <tjalling.dejong@deltares.nl>, Arjen Haag <arjen.haag@deltares.nl>
Classifier: License :: OSI Approved :: GNU General Public License v3 or later (GPLv3+)
Project-URL: Home, https://github.com/Deltares-research/EO-floods
